### 题目

> **1.（选做）**自己写一个简单的 Hello.java，里面需要涉及基本类型，四则运行，if 和 for，然后自己分析一下对应的字节码，有问题群里讨论。



### 源代码

```java
public class Hello{

	byte b = 12;
	short s = 199;
	int age = 23;
	long m = 111L;
	double d = 1.0d;
	float f = 3.3f;
	char c = 'a';
	boolean flag = false;
	
	/**
	 * 冒泡排序
	 */
	public static void main(String[] args) {
		int[] nums = {2,4,5,26,35,134,3,25,2,35};
		int n = nums.length;
		for (int i = 0;i < n;i++) {
			for (int j = 0;j < n;j++) {
				if (nums[i] < nums[j]) {
					int temp = nums[i];
					nums[i] = nums[j];
					nums[j] = temp;
				}
			}
		}
		for (int num: nums) {
			System.out.print(num+",");
		}
	}
}
```







### Javap命令分析

```shell
javac Hello.java
javap -v -c Hello # JDK16
```



输出及分析

```java
Classfile /D:/Github/Geeeeeek/Geeeeek/01_JVM/1/Hello.class
  Last modified 2021年9月19日; size 1391 bytes   // 最后修改时间  大小
  SHA-256 checksum 4ad4d58624d20fbadf5b93fc9dda9694056711aacfb55468f094ad602afc9f6d
  Compiled from "Hello.java"
public class Hello
  minor version: 0						// 小版本
  major version: 60						// 大版本
  flags: (0x0021) ACC_PUBLIC, ACC_SUPER
  this_class: #8                          // Hello
  super_class: #2                         // java/lang/Object
  interfaces: 0, fields: 8, methods: 2, attributes: 3  // 0个接口 8个属性 2个方法
Constant pool:								// 常量池 ↓ ↓ ↓
   #1 = Methodref          #2.#3          // java/lang/Object."<init>":()V
   #2 = Class              #4             // java/lang/Object
   #3 = NameAndType        #5:#6          // "<init>":()V
   #4 = Utf8               java/lang/Object
   #5 = Utf8               <init>
   #6 = Utf8               ()V
   #7 = Fieldref           #8.#9          // Hello.b:B
   #8 = Class              #10            // Hello
   #9 = NameAndType        #11:#12        // b:B
  #10 = Utf8               Hello
  #11 = Utf8               b
  #12 = Utf8               B
  #13 = Fieldref           #8.#14         // Hello.s:S
  #14 = NameAndType        #15:#16        // s:S
  #15 = Utf8               s
  #16 = Utf8               S
  #17 = Fieldref           #8.#18         // Hello.age:I
  #18 = NameAndType        #19:#20        // age:I
  #19 = Utf8               age
  #20 = Utf8               I
  #21 = Long               111l
  #23 = Fieldref           #8.#24         // Hello.m:J
  #24 = NameAndType        #25:#26        // m:J
  #25 = Utf8               m
  #26 = Utf8               J
  #27 = Fieldref           #8.#28         // Hello.d:D
  #28 = NameAndType        #29:#30        // d:D
  #29 = Utf8               d
  #30 = Utf8               D
  #31 = Float              3.3f
  #32 = Fieldref           #8.#33         // Hello.f:F
  #33 = NameAndType        #34:#35        // f:F
  #34 = Utf8               f
  #35 = Utf8               F
  #36 = Fieldref           #8.#37         // Hello.c:C
  #37 = NameAndType        #38:#39        // c:C
  #38 = Utf8               c
  #39 = Utf8               C
  #40 = Fieldref           #8.#41         // Hello.flag:Z
  #41 = NameAndType        #42:#43        // flag:Z
  #42 = Utf8               flag
  #43 = Utf8               Z
  #44 = Fieldref           #45.#46        // java/lang/System.out:Ljava/io/PrintStream;
  #45 = Class              #47            // java/lang/System
  #46 = NameAndType        #48:#49        // out:Ljava/io/PrintStream;
  #47 = Utf8               java/lang/System
  #48 = Utf8               out
  #49 = Utf8               Ljava/io/PrintStream;
  #50 = InvokeDynamic      #0:#51         // #0:makeConcatWithConstants:(I)Ljava/lang/String;
  #51 = NameAndType        #52:#53        // makeConcatWithConstants:(I)Ljava/lang/String;
  #52 = Utf8               makeConcatWithConstants
  #53 = Utf8               (I)Ljava/lang/String;
  #54 = Methodref          #55.#56        // java/io/PrintStream.print:(Ljava/lang/String;)V
  #55 = Class              #57            // java/io/PrintStream
  #56 = NameAndType        #58:#59        // print:(Ljava/lang/String;)V
  #57 = Utf8               java/io/PrintStream
  #58 = Utf8               print
  #59 = Utf8               (Ljava/lang/String;)V
  #60 = Utf8               Code
  #61 = Utf8               LineNumberTable
  #62 = Utf8               main
  #63 = Utf8               ([Ljava/lang/String;)V
  #64 = Utf8               StackMapTable
  #65 = Class              #66            // "[I"
  #66 = Utf8               [I
  #67 = Utf8               SourceFile
  #68 = Utf8               Hello.java
  #69 = Utf8               BootstrapMethods
  #70 = MethodHandle       6:#71          // REF_invokeStatic java/lang/invoke/StringConcatFactory.makeConcatWithConstants:(Ljava/lang/invoke/MethodHandles$Lookup;Ljava/lang/String;Ljava/lang/invoke/MethodType;Ljava/lang/String;[Ljava/lang/Object;)Ljava/lang/invoke/CallSite;
  #71 = Methodref          #72.#73        // java/lang/invoke/StringConcatFactory.makeConcatWithConstants:(Ljava/lang/invoke/MethodHandles$Lookup;Ljava/lang/String;Ljava/lang/invoke/MethodType;Ljava/lang/String;[Ljava/lang/Object;)Ljava/lang/invoke/CallSite;
  #72 = Class              #74            // java/lang/invoke/StringConcatFactory
  #73 = NameAndType        #52:#75        // makeConcatWithConstants:(Ljava/lang/invoke/MethodHandles$Lookup;Ljava/lang/String;Ljava/lang/invoke/MethodType;Ljava/lang/String;[Ljava/lang/Object;)Ljava/lang/invoke/CallSite;
  #74 = Utf8               java/lang/invoke/StringConcatFactory
  #75 = Utf8               (Ljava/lang/invoke/MethodHandles$Lookup;Ljava/lang/String;Ljava/lang/invoke/MethodType;Ljava/lang/String;[Ljava/lang/Object;)Ljava/lang/invoke/CallSite;
  #76 = String             #77            // \u0001,
  #77 = Utf8               \u0001,
  #78 = Utf8               InnerClasses
  #79 = Class              #80            // java/lang/invoke/MethodHandles$Lookup
  #80 = Utf8               java/lang/invoke/MethodHandles$Lookup
  #81 = Class              #82            // java/lang/invoke/MethodHandles
  #82 = Utf8               java/lang/invoke/MethodHandles
  #83 = Utf8               Lookup
{
  byte b;
    descriptor: B
    flags: (0x0000)

  short s;
    descriptor: S
    flags: (0x0000)

  int age;
    descriptor: I
    flags: (0x0000)

  long m;
    descriptor: J
    flags: (0x0000)

  double d;
    descriptor: D
    flags: (0x0000)

  float f;
    descriptor: F
    flags: (0x0000)

  char c;
    descriptor: C
    flags: (0x0000)

  boolean flag;
    descriptor: Z
    flags: (0x0000)

  public Hello();
    descriptor: ()V							//	自动生成的无参构造
    flags: (0x0001) ACC_PUBLIC
    Code:
      stack=3, locals=1, args_size=1
         0: aload_0
         1: invokespecial #1                  // Method java/lang/Object."<init>":()V
         4: aload_0
         5: bipush        12
         7: putfield      #7                  // Field b:B
        10: aload_0
        11: sipush        199
        14: putfield      #13                 // Field s:S
        17: aload_0
        18: bipush        23
        20: putfield      #17                 // Field age:I
        23: aload_0
        24: ldc2_w        #21                 // long 111l
        27: putfield      #23                 // Field m:J
        30: aload_0
        31: dconst_1
        32: putfield      #27                 // Field d:D
        35: aload_0
        36: ldc           #31                 // float 3.3f
        38: putfield      #32                 // Field f:F
        41: aload_0
        42: bipush        97
        44: putfield      #36                 // Field c:C
        47: aload_0
        48: iconst_0
        49: putfield      #40                 // Field flag:Z
        52: return
      LineNumberTable:							// 对应代码行数
        line 1: 0
        line 3: 4
        line 4: 10
        line 5: 17
        line 6: 23
        line 7: 30
        line 8: 35
        line 9: 41
        line 10: 47

  public static void main(java.lang.String[]);
    descriptor: ([Ljava/lang/String;)V				// main方法
    flags: (0x0009) ACC_PUBLIC, ACC_STATIC
    Code:
      stack=4, locals=7, args_size=1
         0: bipush        10						// 申请10位空间 操作符1位  操作数 1位
         2: newarray       int						// int 数组
         4: dup										// 压栈
         5: iconst_0								// {2,4,5,26,35,134,3,25,2,35};
//当int取值-1~5采用iconst指令，取值-128~127采用bipush指令，取值-32768~32767采用sipush指令，取值-2147483648~2147483647采用 ldc 指令。
         6: iconst_2
         7: iastore
         8: dup
         9: iconst_1
        10: iconst_4
        11: iastore
        12: dup
        13: iconst_2
        14: iconst_5
        15: iastore
        16: dup
        17: iconst_3
        18: bipush        26
        20: iastore
        21: dup
        22: iconst_4
        23: bipush        35
        25: iastore
        26: dup
        27: iconst_5
        28: sipush        134
        31: iastore
        32: dup
        33: bipush        6
        35: iconst_3
        36: iastore
        37: dup
        38: bipush        7
        40: bipush        25
        42: iastore
        43: dup
        44: bipush        8
        46: iconst_2
        47: iastore
        48: dup
        49: bipush        9
        51: bipush        35
        53: iastore									// 流程控制
        54: astore_1
        55: aload_1
        56: arraylength
        57: istore_2
        58: iconst_0
        59: istore_3
        60: iload_3
        61: iload_2
        62: if_icmpge     114							// if 比较		
        65: iconst_0
        66: istore        4
        68: iload         4
        70: iload_2
        71: if_icmpge     108
        74: aload_1
        75: iload_3
        76: iaload
        77: aload_1
        78: iload         4
        80: iaload
        81: if_icmpge     102
        84: aload_1
        85: iload_3
        86: iaload
        87: istore        5
        89: aload_1
        90: iload_3
        91: aload_1
        92: iload         4
        94: iaload
        95: iastore
        96: aload_1
        97: iload         4
        99: iload         5
       101: iastore
       102: iinc          4, 1						// 自增
       105: goto          68						// 跳转
       108: iinc          3, 1
       111: goto          60
       114: aload_1
       115: astore_3
       116: aload_3
       117: arraylength
       118: istore        4
       120: iconst_0
       121: istore        5
       123: iload         5
       125: iload         4
       127: if_icmpge     155
       130: aload_3
       131: iload         5
       133: iaload
       134: istore        6
       136: getstatic     #44                 // Field java/lang/System.out:Ljava/io/PrintStream;
       139: iload         6
       141: invokedynamic #50,  0             // InvokeDynamic #0:makeConcatWithConstants:(I)Ljava/lang/String;
       146: invokevirtual #54                 // Method java/io/PrintStream.print:(Ljava/lang/String;)V
       149: iinc          5, 1
       152: goto          123
       155: return
      LineNumberTable:
        line 16: 0
        line 17: 55
        line 18: 58
        line 19: 65
        line 20: 74
        line 21: 84
        line 22: 89
        line 23: 96
        line 19: 102
        line 18: 108
        line 27: 114
        line 28: 136
        line 27: 149
        line 30: 155
      StackMapTable: number_of_entries = 7
        frame_type = 254 /* append */
          offset_delta = 60
          locals = [ class "[I", int, int ]
        frame_type = 252 /* append */
          offset_delta = 7
          locals = [ int ]
        frame_type = 33 /* same */
        frame_type = 250 /* chop */
          offset_delta = 5
        frame_type = 250 /* chop */
          offset_delta = 5
        frame_type = 254 /* append */
          offset_delta = 8
          locals = [ class "[I", int, int ]
        frame_type = 248 /* chop */
          offset_delta = 31
}
SourceFile: "Hello.java"
BootstrapMethods:
  0: #70 REF_invokeStatic java/lang/invoke/StringConcatFactory.makeConcatWithConstants:(Ljava/lang/invoke/MethodHandles$Lookup;Ljava/lang/String;Ljava/lang/invoke/MethodType;Ljava/lang/String;[Ljava/lang/Object;)Ljava/lang/invoke/CallSite;
    Method arguments:
      #76 \u0001,
InnerClasses:
  public static final #83= #79 of #81;    // Lookup=class java/lang/invoke/MethodHandles$Lookup of class java/lang/invoke/MethodHandles
```